nexinfosys/__init__.py
nexinfosys/basic_usage.py
nexinfosys/basic_usage2.py
nexinfosys/client.py
nexinfosys/req_client.py
nexinfosys_client-0.22.dist-info/LICENSE
nexinfosys_client-0.22.dist-info/METADATA
nexinfosys_client-0.22.dist-info/WHEEL
nexinfosys_client-0.22.dist-info/top_level.txt
nexinfosys_client-0.22.dist-info/RECORD
