Metadata-Version: 2.1
Name: nexinfosys-client
Version: 0.22
Summary: Client to NIS backend
Home-page: https://github.com/MAGIC-nexus/nis-python-client
Author: Rafael Nebot - ITC, SA - DCCT
Author-email: rnebot@itccanarias.org
License: BSD3
Platform: UNKNOWN
Requires-Python: >=3.6
Requires-Dist: requests
Requires-Dist: pandas
Requires-Dist: webdavclient (==1.0.8)
